async_web_server/__init__.py
async_web_server/request_arguments_adapter.py
async_web_server/request_scheduler.py
async_web_server/web_server_app.py
async_web_server/web_server_client.py
ey_ehub_async_web_server-1.0.5.dist-info/METADATA
ey_ehub_async_web_server-1.0.5.dist-info/NOTICE
ey_ehub_async_web_server-1.0.5.dist-info/WHEEL
ey_ehub_async_web_server-1.0.5.dist-info/top_level.txt
ey_ehub_async_web_server-1.0.5.dist-info/RECORD
