Metadata-Version: 2.1
Name: ey-ehub-async-web-server
Version: 1.0.5
Summary: The package includes an implementation of web app service library to handle requests asynchronously.
Home-page: UNKNOWN
Maintainer: EY Ecosystems Hub team
Maintainer-email: 
License: UNKNOWN
Platform: UNKNOWN
Classifier: Programming Language :: Python :: 3.6
Classifier: Programming Language :: Python :: 3.7
Requires-Python: >=3.6,!=3.0.*,!=3.1.*,!=3.2.*,!=3.3.*,!=3.4.*,!=3.5.*
Requires-Dist: requests (==2.23.0)
Requires-Dist: Flask (==1.1.2)
Requires-Dist: msal (==1.16.0)
Requires-Dist: typing (>=3.6) ; python_version=="2.7"
Provides-Extra: all
Requires-Dist: requests (==2.23.0) ; extra == 'all'
Requires-Dist: Flask (==1.1.2) ; extra == 'all'
Requires-Dist: msal (==1.16.0) ; extra == 'all'
